identities/__init__.py
identities/admin.py
identities/apps.py
identities/filters.py
identities/models.py
identities/oidc.py
identities/permissions.py
identities/py.typed
identities/urls.py
identities/user_utils.py
identities/version.py
identities/migrations/0001_initial.py
identities/migrations/0002_remove_tech_account.py
identities/migrations/0003_historicaluser.py
identities/migrations/0004_alter_historicaluser_id.py
identities/migrations/0005_alter_historicalprofile_options_and_more.py
identities/migrations/__init__.py
identities/serializers/__init__.py
identities/serializers/group.py
identities/serializers/permission.py
identities/serializers/profile.py
identities/serializers/user.py
identities/serializers/userinfo.py
identities/serializers/utils.py
identities/tests/__init__.py
identities/tests/factories.py
identities/views/__init__.py
identities/views/group.py
identities/views/permission.py
identities/views/user.py
django_identities-2.3.1.dist-info/METADATA
django_identities-2.3.1.dist-info/WHEEL
django_identities-2.3.1.dist-info/top_level.txt
django_identities-2.3.1.dist-info/RECORD
