Metadata-Version: 2.1
Name: django-identities
Version: 2.3.1
Summary: A django app with authentication related functionality, a custom user model and object level permissions / groups.
Home-page: https://gitlab.com/biomedit/django-identities
Author: Jarosław Surkont, Gerhard Bräunlich, Robin Engler, Christian Ribeaud, François Martin
Author-email: jaroslaw.surkont@unibas.ch, gerhard.braeunlich@id.ethz.ch, robin.engler@sib.swiss, christian.ribeaud@karakun.com, francois.martin@karakun.com
License: LGPL3
Classifier: Programming Language :: Python :: 3
Classifier: Programming Language :: Python :: 3.10
Classifier: Programming Language :: Python :: 3.11
Classifier: License :: OSI Approved :: GNU Lesser General Public License v3 (LGPLv3)
Classifier: Operating System :: OS Independent
Requires-Python: >=3.10
Requires-Dist: Django (>=3.2)
Requires-Dist: djangorestframework (>=3.12)
Requires-Dist: django-simple-history (>=3.1.1)
Requires-Dist: django-guardian (>=2.4)
Requires-Dist: authlib (>=0.15)
Requires-Dist: django-drf-utils (>=2.0.0)
Provides-Extra: dev
Requires-Dist: pylint (==2.17.4) ; extra == 'dev'
Requires-Dist: pylint-django (==2.5.3) ; extra == 'dev'
Requires-Dist: mypy (==1.4.1) ; extra == 'dev'
Requires-Dist: black (==23.7.0) ; extra == 'dev'
Requires-Dist: pytest (==7.4.0) ; extra == 'dev'
Requires-Dist: pytest-django ; extra == 'dev'
Requires-Dist: requests ; extra == 'dev'
Requires-Dist: bandit (==1.7.5) ; extra == 'dev'
Requires-Dist: pytest-factoryboy (==2.5.1) ; extra == 'dev'
Requires-Dist: django-stubs ; extra == 'dev'
Requires-Dist: djangorestframework-stubs ; extra == 'dev'
